pymtom_xop/__init__.py
pymtom_xop/constants.py
pymtom_xop/mtom_attachment.py
pymtom_xop/mtom_transport.py
pymtom_xop/soap_envelope.py
pymtom_xop/xop_package.py
pymtom_xop-0.0.2.dist-info/LICENSE
pymtom_xop-0.0.2.dist-info/METADATA
pymtom_xop-0.0.2.dist-info/WHEEL
pymtom_xop-0.0.2.dist-info/top_level.txt
pymtom_xop-0.0.2.dist-info/RECORD
