Metadata-Version: 2.1
Name: pymtom_xop
Version: 0.0.2
Summary: SOAP MTOM-XOP Support for Python
Author-email: Gabriel Santos <gabrielsantosm2019@gmail.com>
License: MIT License
Project-URL: Homepage, https://github.com/Gebrel07/pymtom-xop.git
Keywords: SOAP,MTOM-XOP,WebService
Classifier: Programming Language :: Python :: 3
Classifier: License :: OSI Approved :: MIT License
Classifier: Operating System :: OS Independent
Classifier: Development Status :: 3 - Alpha
Classifier: Intended Audience :: Developers
Classifier: Natural Language :: English
Requires-Python: >=3.10
License-File: LICENSE
Requires-Dist: zeep >=4.2.1
Provides-Extra: dev
Requires-Dist: pytest >=7.4.0 ; extra == 'dev'
Requires-Dist: twine >=4.0.2 ; extra == 'dev'
